gen_ibans/__init__.py
gen_ibans/__main__.py
gen_ibans/cli.py
gen_ibans/config_manager.py
gen_ibans/downloader.py
gen_ibans/iban_generator.py
gen_ibans-2.1.2.dist-info/licenses/LICENSE
gen_ibans-2.1.2.dist-info/METADATA
gen_ibans-2.1.2.dist-info/WHEEL
gen_ibans-2.1.2.dist-info/entry_points.txt
gen_ibans-2.1.2.dist-info/top_level.txt
gen_ibans-2.1.2.dist-info/RECORD
