Metadata-Version: 2.4
Name: gen-ibans
Version: 2.1.2
Summary: Generate valid German IBANs using Bundesbank data and PRNG
Author: Sebastian Wallat
License: MIT
Project-URL: Homepage, https://github.com/swallat/gen-ibans
Project-URL: Bug Reports, https://github.com/swallat/gen-ibans/issues
Project-URL: Source, https://github.com/swallat/gen-ibans
Keywords: iban,germany,banking,generator,prng,bundesbank
Classifier: Development Status :: 4 - Beta
Classifier: Intended Audience :: Developers
Classifier: Intended Audience :: Financial and Insurance Industry
Classifier: License :: OSI Approved :: MIT License
Classifier: Operating System :: OS Independent
Classifier: Programming Language :: Python :: 3
Classifier: Programming Language :: Python :: 3.8
Classifier: Programming Language :: Python :: 3.9
Classifier: Programming Language :: Python :: 3.10
Classifier: Programming Language :: Python :: 3.11
Classifier: Programming Language :: Python :: 3.12
Classifier: Programming Language :: Python :: 3.13
Classifier: Topic :: Office/Business :: Financial
Classifier: Topic :: Software Development :: Libraries :: Python Modules
Classifier: Topic :: Utilities
Requires-Python: >=3.8
License-File: LICENSE
Requires-Dist: faker>=20.0.0
Requires-Dist: click>=8.0.0
Requires-Dist: click-option-group>=0.5.7
Requires-Dist: platformdirs>=3.0.0
Requires-Dist: confz>=2.0.0
Dynamic: license-file
